xfyunsdkface/__init__.py
xfyunsdkface/anti_spoof_client.py
xfyunsdkface/face_compare_client.py
xfyunsdkface/face_detect_client.py
xfyunsdkface/face_status_client.py
xfyunsdkface/face_verify_client.py
xfyunsdkface/silent_detect_client.py
xfyunsdkface/tup_api_client.py
xfyunsdkface/watermark_verify_client.py
xfyunsdkface-0.0.3.dist-info/LICENSE
xfyunsdkface-0.0.3.dist-info/METADATA
xfyunsdkface-0.0.3.dist-info/WHEEL
xfyunsdkface-0.0.3.dist-info/top_level.txt
xfyunsdkface-0.0.3.dist-info/RECORD
