Metadata-Version: 2.1
Name: xfyunsdkface
Version: 0.0.3
Summary: a sdk face detector for xfyun
Author: zyding6
Author-email: zyding6@iflytek.com
Requires-Python: >=3.7.1
License-File: LICENSE
Requires-Dist: xfyunsdkcore >=0.0.3
Requires-Dist: python-dotenv
